{
  "hour": 0,
  "_pattern": "0시 정상 운영",
  "dataPoints": [
    {
      "minute": 0,
      "timestamp": "00:00",
      "servers": {
        "web-nginx-icn-01": {
          "id": "web-nginx-icn-01",
          "name": "Nginx Web Server 01",
          "hostname": "web-nginx-icn-01.openmanager.kr",
          "type": "web",
          "location": "Seoul-ICN-AZ1",
          "environment": "production",
          "status": "warning",
          "cpu": 78,
          "memory": 41,
          "disk": 28,
          "network": 56,
          "responseTime": 200,
          "uptime": 2639092,
          "ip": "10.10.1.11",
          "os": "Ubuntu 22.04 LTS",
          "specs": {
            "cpu_cores": 4,
            "memory_gb": 8,
            "disk_gb": 100
          },
          "services": [
            {
              "name": "nginx",
              "status": "running",
              "health": "warning",
              "message": "Elevated cpu usage"
            },
            {
              "name": "php-fpm",
              "status": "running",
              "health": "warning",
              "message": "Elevated cpu usage"
            }
          ],
          "processes": 175,
          "logs": [
            {
              "timestamp": "00:00:00",
              "level": "WARN",
              "message": "[WARNING] CPU usage at 78% - 새벽 배치 크론 작업으로 CPU 증가"
            }
          ]
        },
        "web-nginx-icn-02": {
          "id": "web-nginx-icn-02",
          "name": "Nginx Web Server 02",
          "hostname": "web-nginx-icn-02.openmanager.kr",
          "type": "web",
          "location": "Seoul-ICN-AZ2",
          "environment": "production",
          "status": "online",
          "cpu": 29,
          "memory": 40,
          "disk": 28,
          "network": 58,
          "responseTime": 153,
          "uptime": 2651315,
          "ip": "10.10.1.12",
          "os": "Ubuntu 22.04 LTS",
          "specs": {
            "cpu_cores": 4,
            "memory_gb": 8,
            "disk_gb": 100
          },
          "services": [],
          "processes": 100,
          "logs": []
        },
        "web-nginx-pus-01": {
          "id": "web-nginx-pus-01",
          "name": "Nginx Web Server DR",
          "hostname": "web-nginx-pus-01.openmanager.kr",
          "type": "web",
          "location": "Busan-PUS-AZ1",
          "environment": "production",
          "status": "online",
          "cpu": 18,
          "memory": 35,
          "disk": 24,
          "network": 41,
          "responseTime": 168,
          "uptime": 2631988,
          "ip": "10.20.1.11",
          "os": "Ubuntu 22.04 LTS",
          "specs": {
            "cpu_cores": 4,
            "memory_gb": 8,
            "disk_gb": 100
          },
          "services": [],
          "processes": 146,
          "logs": []
        },
        "api-was-icn-01": {
          "id": "api-was-icn-01",
          "name": "WAS API Server 01",
          "hostname": "api-was-icn-01.openmanager.kr",
          "type": "application",
          "location": "Seoul-ICN-AZ1",
          "environment": "production",
          "status": "online",
          "cpu": 48,
          "memory": 51,
          "disk": 36,
          "network": 50,
          "responseTime": 128,
          "uptime": 2676156,
          "ip": "10.10.2.11",
          "os": "Ubuntu 22.04 LTS",
          "specs": {
            "cpu_cores": 8,
            "memory_gb": 16,
            "disk_gb": 200
          },
          "services": [],
          "processes": 118,
          "logs": []
        },
        "api-was-icn-02": {
          "id": "api-was-icn-02",
          "name": "WAS API Server 02",
          "hostname": "api-was-icn-02.openmanager.kr",
          "type": "application",
          "location": "Seoul-ICN-AZ2",
          "environment": "production",
          "status": "online",
          "cpu": 43,
          "memory": 51,
          "disk": 30,
          "network": 48,
          "responseTime": 171,
          "uptime": 2659554,
          "ip": "10.10.2.12",
          "os": "Ubuntu 22.04 LTS",
          "specs": {
            "cpu_cores": 8,
            "memory_gb": 16,
            "disk_gb": 200
          },
          "services": [],
          "processes": 148,
          "logs": []
        },
        "api-was-pus-01": {
          "id": "api-was-pus-01",
          "name": "WAS API Server DR",
          "hostname": "api-was-pus-01.openmanager.kr",
          "type": "application",
          "location": "Busan-PUS-AZ1",
          "environment": "production",
          "status": "online",
          "cpu": 22,
          "memory": 41,
          "disk": 27,
          "network": 38,
          "responseTime": 177,
          "uptime": 2599733,
          "ip": "10.20.2.11",
          "os": "Ubuntu 22.04 LTS",
          "specs": {
            "cpu_cores": 8,
            "memory_gb": 16,
            "disk_gb": 200
          },
          "services": [],
          "processes": 103,
          "logs": []
        },
        "db-mysql-icn-primary": {
          "id": "db-mysql-icn-primary",
          "name": "MySQL Primary",
          "hostname": "db-mysql-icn-primary.openmanager.kr",
          "type": "database",
          "location": "Seoul-ICN-AZ1",
          "environment": "production",
          "status": "critical",
          "cpu": 52,
          "memory": 69,
          "disk": 92,
          "network": 37,
          "responseTime": 380,
          "uptime": 2607463,
          "ip": "10.10.3.11",
          "os": "Ubuntu 22.04 LTS",
          "specs": {
            "cpu_cores": 16,
            "memory_gb": 64,
            "disk_gb": 1000
          },
          "services": [
            {
              "name": "mysqld",
              "status": "degraded",
              "health": "critical",
              "message": "High disk usage affecting mysqld"
            },
            {
              "name": "mysql-router",
              "status": "degraded",
              "health": "critical",
              "message": "High disk usage affecting mysql-router"
            }
          ],
          "processes": 120,
          "logs": [
            {
              "timestamp": "00:00:00",
              "level": "ERROR",
              "message": "[CRITICAL] DISK usage reached 92% - 새벽 자동 백업 + 바이너리 로그 누적으로 디스크 위험"
            },
            {
              "timestamp": "00:01:00",
              "level": "WARN",
              "message": "[ALERT] Threshold exceeded: disk > 90%. Immediate action required."
            }
          ]
        },
        "db-mysql-icn-replica": {
          "id": "db-mysql-icn-replica",
          "name": "MySQL Replica",
          "hostname": "db-mysql-icn-replica.openmanager.kr",
          "type": "database",
          "location": "Seoul-ICN-AZ2",
          "environment": "production",
          "status": "online",
          "cpu": 36,
          "memory": 58,
          "disk": 41,
          "network": 34,
          "responseTime": 45,
          "uptime": 2592654,
          "ip": "10.10.3.12",
          "os": "Ubuntu 22.04 LTS",
          "specs": {
            "cpu_cores": 16,
            "memory_gb": 64,
            "disk_gb": 1000
          },
          "services": [],
          "processes": 141,
          "logs": []
        },
        "db-mysql-pus-dr": {
          "id": "db-mysql-pus-dr",
          "name": "MySQL DR Replica",
          "hostname": "db-mysql-pus-dr.openmanager.kr",
          "type": "database",
          "location": "Busan-PUS-AZ1",
          "environment": "production",
          "status": "online",
          "cpu": 17,
          "memory": 47,
          "disk": 40,
          "network": 29,
          "responseTime": 58,
          "uptime": 2653626,
          "ip": "10.20.3.11",
          "os": "Ubuntu 22.04 LTS",
          "specs": {
            "cpu_cores": 16,
            "memory_gb": 64,
            "disk_gb": 1000
          },
          "services": [],
          "processes": 131,
          "logs": []
        },
        "cache-redis-icn-01": {
          "id": "cache-redis-icn-01",
          "name": "Redis Cache 01",
          "hostname": "cache-redis-icn-01.openmanager.kr",
          "type": "cache",
          "location": "Seoul-ICN-AZ1",
          "environment": "production",
          "status": "warning",
          "cpu": 29,
          "memory": 88,
          "disk": 20,
          "network": 45,
          "responseTime": 200,
          "uptime": 2606881,
          "ip": "10.10.4.11",
          "os": "Ubuntu 22.04 LTS",
          "specs": {
            "cpu_cores": 4,
            "memory_gb": 32,
            "disk_gb": 50
          },
          "services": [
            {
              "name": "redis-server",
              "status": "running",
              "health": "warning",
              "message": "Elevated memory usage"
            },
            {
              "name": "redis-sentinel",
              "status": "running",
              "health": "warning",
              "message": "Elevated memory usage"
            }
          ],
          "processes": 111,
          "logs": [
            {
              "timestamp": "00:00:00",
              "level": "WARN",
              "message": "[WARNING] MEMORY usage at 88% - Redis 캐시 메모리 누적으로 경고 수준"
            }
          ]
        },
        "cache-redis-icn-02": {
          "id": "cache-redis-icn-02",
          "name": "Redis Cache 02",
          "hostname": "cache-redis-icn-02.openmanager.kr",
          "type": "cache",
          "location": "Seoul-ICN-AZ2",
          "environment": "production",
          "status": "online",
          "cpu": 24,
          "memory": 74,
          "disk": 18,
          "network": 45,
          "responseTime": 16,
          "uptime": 2628728,
          "ip": "10.10.4.12",
          "os": "Ubuntu 22.04 LTS",
          "specs": {
            "cpu_cores": 4,
            "memory_gb": 32,
            "disk_gb": 50
          },
          "services": [],
          "processes": 115,
          "logs": []
        },
        "storage-nfs-icn-01": {
          "id": "storage-nfs-icn-01",
          "name": "NFS Storage 01",
          "hostname": "storage-nfs-icn-01.openmanager.kr",
          "type": "storage",
          "location": "Seoul-ICN-AZ1",
          "environment": "production",
          "status": "online",
          "cpu": 32,
          "memory": 42,
          "disk": 66,
          "network": 45,
          "responseTime": 145,
          "uptime": 2668617,
          "ip": "10.10.5.11",
          "os": "Ubuntu 22.04 LTS",
          "specs": {
            "cpu_cores": 4,
            "memory_gb": 16,
            "disk_gb": 5000
          },
          "services": [],
          "processes": 124,
          "logs": []
        },
        "storage-s3gw-pus-01": {
          "id": "storage-s3gw-pus-01",
          "name": "S3 Gateway DR",
          "hostname": "storage-s3gw-pus-01.openmanager.kr",
          "type": "storage",
          "location": "Busan-PUS-DR",
          "environment": "production",
          "status": "online",
          "cpu": 16,
          "memory": 34,
          "disk": 52,
          "network": 56,
          "responseTime": 147,
          "uptime": 2670131,
          "ip": "10.20.5.11",
          "os": "Ubuntu 22.04 LTS",
          "specs": {
            "cpu_cores": 2,
            "memory_gb": 8,
            "disk_gb": 200
          },
          "services": [],
          "processes": 116,
          "logs": []
        },
        "lb-haproxy-icn-01": {
          "id": "lb-haproxy-icn-01",
          "name": "HAProxy LB 01",
          "hostname": "lb-haproxy-icn-01.openmanager.kr",
          "type": "loadbalancer",
          "location": "Seoul-ICN-AZ1",
          "environment": "production",
          "status": "online",
          "cpu": 37,
          "memory": 37,
          "disk": 17,
          "network": 74,
          "responseTime": 144,
          "uptime": 2612470,
          "ip": "10.10.6.11",
          "os": "Ubuntu 22.04 LTS",
          "specs": {
            "cpu_cores": 4,
            "memory_gb": 8,
            "disk_gb": 50
          },
          "services": [],
          "processes": 102,
          "logs": []
        },
        "lb-haproxy-pus-01": {
          "id": "lb-haproxy-pus-01",
          "name": "HAProxy LB DR",
          "hostname": "lb-haproxy-pus-01.openmanager.kr",
          "type": "loadbalancer",
          "location": "Busan-PUS-DR",
          "environment": "production",
          "status": "online",
          "cpu": 38,
          "memory": 32,
          "disk": 14,
          "network": 71,
          "responseTime": 171,
          "uptime": 2630713,
          "ip": "10.20.6.11",
          "os": "Ubuntu 22.04 LTS",
          "specs": {
            "cpu_cores": 4,
            "memory_gb": 8,
            "disk_gb": 50
          },
          "services": [],
          "processes": 148,
          "logs": []
        }
      }
    },
    {
      "minute": 10,
      "timestamp": "00:10",
      "servers": {
        "web-nginx-icn-01": {
          "id": "web-nginx-icn-01",
          "name": "Nginx Web Server 01",
          "hostname": "web-nginx-icn-01.openmanager.kr",
          "type": "web",
          "location": "Seoul-ICN-AZ1",
          "environment": "production",
          "status": "warning",
          "cpu": 78,
          "memory": 41,
          "disk": 30,
          "network": 64,
          "responseTime": 200,
          "uptime": 2616287,
          "ip": "10.10.1.11",
          "os": "Ubuntu 22.04 LTS",
          "specs": {
            "cpu_cores": 4,
            "memory_gb": 8,
            "disk_gb": 100
          },
          "services": [
            {
              "name": "nginx",
              "status": "running",
              "health": "warning",
              "message": "Elevated cpu usage"
            },
            {
              "name": "php-fpm",
              "status": "running",
              "health": "warning",
              "message": "Elevated cpu usage"
            }
          ],
          "processes": 175,
          "logs": [
            {
              "timestamp": "00:10:00",
              "level": "WARN",
              "message": "[WARNING] CPU usage at 78% - 새벽 배치 크론 작업으로 CPU 증가"
            }
          ]
        },
        "web-nginx-icn-02": {
          "id": "web-nginx-icn-02",
          "name": "Nginx Web Server 02",
          "hostname": "web-nginx-icn-02.openmanager.kr",
          "type": "web",
          "location": "Seoul-ICN-AZ2",
          "environment": "production",
          "status": "online",
          "cpu": 28,
          "memory": 44,
          "disk": 28,
          "network": 56,
          "responseTime": 143,
          "uptime": 2651906,
          "ip": "10.10.1.12",
          "os": "Ubuntu 22.04 LTS",
          "specs": {
            "cpu_cores": 4,
            "memory_gb": 8,
            "disk_gb": 100
          },
          "services": [],
          "processes": 129,
          "logs": []
        },
        "web-nginx-pus-01": {
          "id": "web-nginx-pus-01",
          "name": "Nginx Web Server DR",
          "hostname": "web-nginx-pus-01.openmanager.kr",
          "type": "web",
          "location": "Busan-PUS-AZ1",
          "environment": "production",
          "status": "online",
          "cpu": 19,
          "memory": 34,
          "disk": 24,
          "network": 43,
          "responseTime": 123,
          "uptime": 2606100,
          "ip": "10.20.1.11",
          "os": "Ubuntu 22.04 LTS",
          "specs": {
            "cpu_cores": 4,
            "memory_gb": 8,
            "disk_gb": 100
          },
          "services": [],
          "processes": 122,
          "logs": []
        },
        "api-was-icn-01": {
          "id": "api-was-icn-01",
          "name": "WAS API Server 01",
          "hostname": "api-was-icn-01.openmanager.kr",
          "type": "application",
          "location": "Seoul-ICN-AZ1",
          "environment": "production",
          "status": "online",
          "cpu": 44,
          "memory": 53,
          "disk": 36,
          "network": 54,
          "responseTime": 157,
          "uptime": 2664471,
          "ip": "10.10.2.11",
          "os": "Ubuntu 22.04 LTS",
          "specs": {
            "cpu_cores": 8,
            "memory_gb": 16,
            "disk_gb": 200
          },
          "services": [],
          "processes": 100,
          "logs": []
        },
        "api-was-icn-02": {
          "id": "api-was-icn-02",
          "name": "WAS API Server 02",
          "hostname": "api-was-icn-02.openmanager.kr",
          "type": "application",
          "location": "Seoul-ICN-AZ2",
          "environment": "production",
          "status": "online",
          "cpu": 40,
          "memory": 54,
          "disk": 32,
          "network": 51,
          "responseTime": 127,
          "uptime": 2651338,
          "ip": "10.10.2.12",
          "os": "Ubuntu 22.04 LTS",
          "specs": {
            "cpu_cores": 8,
            "memory_gb": 16,
            "disk_gb": 200
          },
          "services": [],
          "processes": 102,
          "logs": []
        },
        "api-was-pus-01": {
          "id": "api-was-pus-01",
          "name": "WAS API Server DR",
          "hostname": "api-was-pus-01.openmanager.kr",
          "type": "application",
          "location": "Busan-PUS-AZ1",
          "environment": "production",
          "status": "online",
          "cpu": 28,
          "memory": 37,
          "disk": 29,
          "network": 39,
          "responseTime": 150,
          "uptime": 2635875,
          "ip": "10.20.2.11",
          "os": "Ubuntu 22.04 LTS",
          "specs": {
            "cpu_cores": 8,
            "memory_gb": 16,
            "disk_gb": 200
          },
          "services": [],
          "processes": 146,
          "logs": []
        },
        "db-mysql-icn-primary": {
          "id": "db-mysql-icn-primary",
          "name": "MySQL Primary",
          "hostname": "db-mysql-icn-primary.openmanager.kr",
          "type": "database",
          "location": "Seoul-ICN-AZ1",
          "environment": "production",
          "status": "critical",
          "cpu": 59,
          "memory": 71,
          "disk": 92,
          "network": 36,
          "responseTime": 380,
          "uptime": 2609849,
          "ip": "10.10.3.11",
          "os": "Ubuntu 22.04 LTS",
          "specs": {
            "cpu_cores": 16,
            "memory_gb": 64,
            "disk_gb": 1000
          },
          "services": [
            {
              "name": "mysqld",
              "status": "degraded",
              "health": "critical",
              "message": "High disk usage affecting mysqld"
            },
            {
              "name": "mysql-router",
              "status": "degraded",
              "health": "critical",
              "message": "High disk usage affecting mysql-router"
            }
          ],
          "processes": 138,
          "logs": [
            {
              "timestamp": "00:10:00",
              "level": "ERROR",
              "message": "[CRITICAL] DISK usage reached 92% - 새벽 자동 백업 + 바이너리 로그 누적으로 디스크 위험"
            },
            {
              "timestamp": "00:11:00",
              "level": "WARN",
              "message": "[ALERT] Threshold exceeded: disk > 90%. Immediate action required."
            }
          ]
        },
        "db-mysql-icn-replica": {
          "id": "db-mysql-icn-replica",
          "name": "MySQL Replica",
          "hostname": "db-mysql-icn-replica.openmanager.kr",
          "type": "database",
          "location": "Seoul-ICN-AZ2",
          "environment": "production",
          "status": "online",
          "cpu": 40,
          "memory": 62,
          "disk": 43,
          "network": 33,
          "responseTime": 57,
          "uptime": 2656155,
          "ip": "10.10.3.12",
          "os": "Ubuntu 22.04 LTS",
          "specs": {
            "cpu_cores": 16,
            "memory_gb": 64,
            "disk_gb": 1000
          },
          "services": [],
          "processes": 111,
          "logs": []
        },
        "db-mysql-pus-dr": {
          "id": "db-mysql-pus-dr",
          "name": "MySQL DR Replica",
          "hostname": "db-mysql-pus-dr.openmanager.kr",
          "type": "database",
          "location": "Busan-PUS-AZ1",
          "environment": "production",
          "status": "online",
          "cpu": 21,
          "memory": 47,
          "disk": 38,
          "network": 23,
          "responseTime": 41,
          "uptime": 2623466,
          "ip": "10.20.3.11",
          "os": "Ubuntu 22.04 LTS",
          "specs": {
            "cpu_cores": 16,
            "memory_gb": 64,
            "disk_gb": 1000
          },
          "services": [],
          "processes": 115,
          "logs": []
        },
        "cache-redis-icn-01": {
          "id": "cache-redis-icn-01",
          "name": "Redis Cache 01",
          "hostname": "cache-redis-icn-01.openmanager.kr",
          "type": "cache",
          "location": "Seoul-ICN-AZ1",
          "environment": "production",
          "status": "warning",
          "cpu": 20,
          "memory": 88,
          "disk": 20,
          "network": 46,
          "responseTime": 200,
          "uptime": 2635512,
          "ip": "10.10.4.11",
          "os": "Ubuntu 22.04 LTS",
          "specs": {
            "cpu_cores": 4,
            "memory_gb": 32,
            "disk_gb": 50
          },
          "services": [
            {
              "name": "redis-server",
              "status": "running",
              "health": "warning",
              "message": "Elevated memory usage"
            },
            {
              "name": "redis-sentinel",
              "status": "running",
              "health": "warning",
              "message": "Elevated memory usage"
            }
          ],
          "processes": 126,
          "logs": [
            {
              "timestamp": "00:10:00",
              "level": "WARN",
              "message": "[WARNING] MEMORY usage at 88% - Redis 캐시 메모리 누적으로 경고 수준"
            }
          ]
        },
        "cache-redis-icn-02": {
          "id": "cache-redis-icn-02",
          "name": "Redis Cache 02",
          "hostname": "cache-redis-icn-02.openmanager.kr",
          "type": "cache",
          "location": "Seoul-ICN-AZ2",
          "environment": "production",
          "status": "online",
          "cpu": 18,
          "memory": 70,
          "disk": 16,
          "network": 40,
          "responseTime": 21,
          "uptime": 2676323,
          "ip": "10.10.4.12",
          "os": "Ubuntu 22.04 LTS",
          "specs": {
            "cpu_cores": 4,
            "memory_gb": 32,
            "disk_gb": 50
          },
          "services": [],
          "processes": 129,
          "logs": []
        },
        "storage-nfs-icn-01": {
          "id": "storage-nfs-icn-01",
          "name": "NFS Storage 01",
          "hostname": "storage-nfs-icn-01.openmanager.kr",
          "type": "storage",
          "location": "Seoul-ICN-AZ1",
          "environment": "production",
          "status": "online",
          "cpu": 27,
          "memory": 42,
          "disk": 66,
          "network": 54,
          "responseTime": 162,
          "uptime": 2676140,
          "ip": "10.10.5.11",
          "os": "Ubuntu 22.04 LTS",
          "specs": {
            "cpu_cores": 4,
            "memory_gb": 16,
            "disk_gb": 5000
          },
          "services": [],
          "processes": 120,
          "logs": []
        },
        "storage-s3gw-pus-01": {
          "id": "storage-s3gw-pus-01",
          "name": "S3 Gateway DR",
          "hostname": "storage-s3gw-pus-01.openmanager.kr",
          "type": "storage",
          "location": "Busan-PUS-DR",
          "environment": "production",
          "status": "online",
          "cpu": 16,
          "memory": 35,
          "disk": 55,
          "network": 57,
          "responseTime": 155,
          "uptime": 2611808,
          "ip": "10.20.5.11",
          "os": "Ubuntu 22.04 LTS",
          "specs": {
            "cpu_cores": 2,
            "memory_gb": 8,
            "disk_gb": 200
          },
          "services": [],
          "processes": 143,
          "logs": []
        },
        "lb-haproxy-icn-01": {
          "id": "lb-haproxy-icn-01",
          "name": "HAProxy LB 01",
          "hostname": "lb-haproxy-icn-01.openmanager.kr",
          "type": "loadbalancer",
          "location": "Seoul-ICN-AZ1",
          "environment": "production",
          "status": "online",
          "cpu": 42,
          "memory": 34,
          "disk": 15,
          "network": 72,
          "responseTime": 143,
          "uptime": 2613139,
          "ip": "10.10.6.11",
          "os": "Ubuntu 22.04 LTS",
          "specs": {
            "cpu_cores": 4,
            "memory_gb": 8,
            "disk_gb": 50
          },
          "services": [],
          "processes": 123,
          "logs": []
        },
        "lb-haproxy-pus-01": {
          "id": "lb-haproxy-pus-01",
          "name": "HAProxy LB DR",
          "hostname": "lb-haproxy-pus-01.openmanager.kr",
          "type": "loadbalancer",
          "location": "Busan-PUS-DR",
          "environment": "production",
          "status": "online",
          "cpu": 41,
          "memory": 29,
          "disk": 15,
          "network": 66,
          "responseTime": 130,
          "uptime": 2594506,
          "ip": "10.20.6.11",
          "os": "Ubuntu 22.04 LTS",
          "specs": {
            "cpu_cores": 4,
            "memory_gb": 8,
            "disk_gb": 50
          },
          "services": [],
          "processes": 148,
          "logs": []
        }
      }
    },
    {
      "minute": 20,
      "timestamp": "00:20",
      "servers": {
        "web-nginx-icn-01": {
          "id": "web-nginx-icn-01",
          "name": "Nginx Web Server 01",
          "hostname": "web-nginx-icn-01.openmanager.kr",
          "type": "web",
          "location": "Seoul-ICN-AZ1",
          "environment": "production",
          "status": "warning",
          "cpu": 78,
          "memory": 43,
          "disk": 28,
          "network": 60,
          "responseTime": 200,
          "uptime": 2646504,
          "ip": "10.10.1.11",
          "os": "Ubuntu 22.04 LTS",
          "specs": {
            "cpu_cores": 4,
            "memory_gb": 8,
            "disk_gb": 100
          },
          "services": [
            {
              "name": "nginx",
              "status": "running",
              "health": "warning",
              "message": "Elevated cpu usage"
            },
            {
              "name": "php-fpm",
              "status": "running",
              "health": "warning",
              "message": "Elevated cpu usage"
            }
          ],
          "processes": 175,
          "logs": [
            {
              "timestamp": "00:20:00",
              "level": "WARN",
              "message": "[WARNING] CPU usage at 78% - 새벽 배치 크론 작업으로 CPU 증가"
            }
          ]
        },
        "web-nginx-icn-02": {
          "id": "web-nginx-icn-02",
          "name": "Nginx Web Server 02",
          "hostname": "web-nginx-icn-02.openmanager.kr",
          "type": "web",
          "location": "Seoul-ICN-AZ2",
          "environment": "production",
          "status": "online",
          "cpu": 33,
          "memory": 42,
          "disk": 29,
          "network": 59,
          "responseTime": 175,
          "uptime": 2653239,
          "ip": "10.10.1.12",
          "os": "Ubuntu 22.04 LTS",
          "specs": {
            "cpu_cores": 4,
            "memory_gb": 8,
            "disk_gb": 100
          },
          "services": [],
          "processes": 134,
          "logs": []
        },
        "web-nginx-pus-01": {
          "id": "web-nginx-pus-01",
          "name": "Nginx Web Server DR",
          "hostname": "web-nginx-pus-01.openmanager.kr",
          "type": "web",
          "location": "Busan-PUS-AZ1",
          "environment": "production",
          "status": "online",
          "cpu": 16,
          "memory": 38,
          "disk": 23,
          "network": 39,
          "responseTime": 142,
          "uptime": 2617563,
          "ip": "10.20.1.11",
          "os": "Ubuntu 22.04 LTS",
          "specs": {
            "cpu_cores": 4,
            "memory_gb": 8,
            "disk_gb": 100
          },
          "services": [],
          "processes": 124,
          "logs": []
        },
        "api-was-icn-01": {
          "id": "api-was-icn-01",
          "name": "WAS API Server 01",
          "hostname": "api-was-icn-01.openmanager.kr",
          "type": "application",
          "location": "Seoul-ICN-AZ1",
          "environment": "production",
          "status": "online",
          "cpu": 48,
          "memory": 58,
          "disk": 33,
          "network": 46,
          "responseTime": 120,
          "uptime": 2651794,
          "ip": "10.10.2.11",
          "os": "Ubuntu 22.04 LTS",
          "specs": {
            "cpu_cores": 8,
            "memory_gb": 16,
            "disk_gb": 200
          },
          "services": [],
          "processes": 122,
          "logs": []
        },
        "api-was-icn-02": {
          "id": "api-was-icn-02",
          "name": "WAS API Server 02",
          "hostname": "api-was-icn-02.openmanager.kr",
          "type": "application",
          "location": "Seoul-ICN-AZ2",
          "environment": "production",
          "status": "online",
          "cpu": 41,
          "memory": 54,
          "disk": 32,
          "network": 52,
          "responseTime": 178,
          "uptime": 2603559,
          "ip": "10.10.2.12",
          "os": "Ubuntu 22.04 LTS",
          "specs": {
            "cpu_cores": 8,
            "memory_gb": 16,
            "disk_gb": 200
          },
          "services": [],
          "processes": 142,
          "logs": []
        },
        "api-was-pus-01": {
          "id": "api-was-pus-01",
          "name": "WAS API Server DR",
          "hostname": "api-was-pus-01.openmanager.kr",
          "type": "application",
          "location": "Busan-PUS-AZ1",
          "environment": "production",
          "status": "online",
          "cpu": 23,
          "memory": 43,
          "disk": 27,
          "network": 39,
          "responseTime": 146,
          "uptime": 2597607,
          "ip": "10.20.2.11",
          "os": "Ubuntu 22.04 LTS",
          "specs": {
            "cpu_cores": 8,
            "memory_gb": 16,
            "disk_gb": 200
          },
          "services": [],
          "processes": 144,
          "logs": []
        },
        "db-mysql-icn-primary": {
          "id": "db-mysql-icn-primary",
          "name": "MySQL Primary",
          "hostname": "db-mysql-icn-primary.openmanager.kr",
          "type": "database",
          "location": "Seoul-ICN-AZ1",
          "environment": "production",
          "status": "critical",
          "cpu": 51,
          "memory": 72,
          "disk": 92,
          "network": 35,
          "responseTime": 380,
          "uptime": 2645109,
          "ip": "10.10.3.11",
          "os": "Ubuntu 22.04 LTS",
          "specs": {
            "cpu_cores": 16,
            "memory_gb": 64,
            "disk_gb": 1000
          },
          "services": [
            {
              "name": "mysqld",
              "status": "degraded",
              "health": "critical",
              "message": "High disk usage affecting mysqld"
            },
            {
              "name": "mysql-router",
              "status": "degraded",
              "health": "critical",
              "message": "High disk usage affecting mysql-router"
            }
          ],
          "processes": 137,
          "logs": [
            {
              "timestamp": "00:20:00",
              "level": "ERROR",
              "message": "[CRITICAL] DISK usage reached 92% - 새벽 자동 백업 + 바이너리 로그 누적으로 디스크 위험"
            },
            {
              "timestamp": "00:21:00",
              "level": "WARN",
              "message": "[ALERT] Threshold exceeded: disk > 90%. Immediate action required."
            }
          ]
        },
        "db-mysql-icn-replica": {
          "id": "db-mysql-icn-replica",
          "name": "MySQL Replica",
          "hostname": "db-mysql-icn-replica.openmanager.kr",
          "type": "database",
          "location": "Seoul-ICN-AZ2",
          "environment": "production",
          "status": "online",
          "cpu": 39,
          "memory": 61,
          "disk": 42,
          "network": 32,
          "responseTime": 60,
          "uptime": 2676146,
          "ip": "10.10.3.12",
          "os": "Ubuntu 22.04 LTS",
          "specs": {
            "cpu_cores": 16,
            "memory_gb": 64,
            "disk_gb": 1000
          },
          "services": [],
          "processes": 139,
          "logs": []
        },
        "db-mysql-pus-dr": {
          "id": "db-mysql-pus-dr",
          "name": "MySQL DR Replica",
          "hostname": "db-mysql-pus-dr.openmanager.kr",
          "type": "database",
          "location": "Busan-PUS-AZ1",
          "environment": "production",
          "status": "online",
          "cpu": 17,
          "memory": 44,
          "disk": 40,
          "network": 26,
          "responseTime": 59,
          "uptime": 2605932,
          "ip": "10.20.3.11",
          "os": "Ubuntu 22.04 LTS",
          "specs": {
            "cpu_cores": 16,
            "memory_gb": 64,
            "disk_gb": 1000
          },
          "services": [],
          "processes": 122,
          "logs": []
        },
        "cache-redis-icn-01": {
          "id": "cache-redis-icn-01",
          "name": "Redis Cache 01",
          "hostname": "cache-redis-icn-01.openmanager.kr",
          "type": "cache",
          "location": "Seoul-ICN-AZ1",
          "environment": "production",
          "status": "warning",
          "cpu": 29,
          "memory": 88,
          "disk": 20,
          "network": 43,
          "responseTime": 200,
          "uptime": 2641038,
          "ip": "10.10.4.11",
          "os": "Ubuntu 22.04 LTS",
          "specs": {
            "cpu_cores": 4,
            "memory_gb": 32,
            "disk_gb": 50
          },
          "services": [
            {
              "name": "redis-server",
              "status": "running",
              "health": "warning",
              "message": "Elevated memory usage"
            },
            {
              "name": "redis-sentinel",
              "status": "running",
              "health": "warning",
              "message": "Elevated memory usage"
            }
          ],
          "processes": 116,
          "logs": [
            {
              "timestamp": "00:20:00",
              "level": "WARN",
              "message": "[WARNING] MEMORY usage at 88% - Redis 캐시 메모리 누적으로 경고 수준"
            }
          ]
        },
        "cache-redis-icn-02": {
          "id": "cache-redis-icn-02",
          "name": "Redis Cache 02",
          "hostname": "cache-redis-icn-02.openmanager.kr",
          "type": "cache",
          "location": "Seoul-ICN-AZ2",
          "environment": "production",
          "status": "online",
          "cpu": 21,
          "memory": 72,
          "disk": 17,
          "network": 40,
          "responseTime": 20,
          "uptime": 2644306,
          "ip": "10.10.4.12",
          "os": "Ubuntu 22.04 LTS",
          "specs": {
            "cpu_cores": 4,
            "memory_gb": 32,
            "disk_gb": 50
          },
          "services": [],
          "processes": 117,
          "logs": []
        },
        "storage-nfs-icn-01": {
          "id": "storage-nfs-icn-01",
          "name": "NFS Storage 01",
          "hostname": "storage-nfs-icn-01.openmanager.kr",
          "type": "storage",
          "location": "Seoul-ICN-AZ1",
          "environment": "production",
          "status": "online",
          "cpu": 28,
          "memory": 42,
          "disk": 66,
          "network": 51,
          "responseTime": 163,
          "uptime": 2647735,
          "ip": "10.10.5.11",
          "os": "Ubuntu 22.04 LTS",
          "specs": {
            "cpu_cores": 4,
            "memory_gb": 16,
            "disk_gb": 5000
          },
          "services": [],
          "processes": 147,
          "logs": []
        },
        "storage-s3gw-pus-01": {
          "id": "storage-s3gw-pus-01",
          "name": "S3 Gateway DR",
          "hostname": "storage-s3gw-pus-01.openmanager.kr",
          "type": "storage",
          "location": "Busan-PUS-DR",
          "environment": "production",
          "status": "online",
          "cpu": 23,
          "memory": 37,
          "disk": 52,
          "network": 61,
          "responseTime": 128,
          "uptime": 2655926,
          "ip": "10.20.5.11",
          "os": "Ubuntu 22.04 LTS",
          "specs": {
            "cpu_cores": 2,
            "memory_gb": 8,
            "disk_gb": 200
          },
          "services": [],
          "processes": 134,
          "logs": []
        },
        "lb-haproxy-icn-01": {
          "id": "lb-haproxy-icn-01",
          "name": "HAProxy LB 01",
          "hostname": "lb-haproxy-icn-01.openmanager.kr",
          "type": "loadbalancer",
          "location": "Seoul-ICN-AZ1",
          "environment": "production",
          "status": "online",
          "cpu": 36,
          "memory": 32,
          "disk": 13,
          "network": 71,
          "responseTime": 163,
          "uptime": 2661085,
          "ip": "10.10.6.11",
          "os": "Ubuntu 22.04 LTS",
          "specs": {
            "cpu_cores": 4,
            "memory_gb": 8,
            "disk_gb": 50
          },
          "services": [],
          "processes": 123,
          "logs": []
        },
        "lb-haproxy-pus-01": {
          "id": "lb-haproxy-pus-01",
          "name": "HAProxy LB DR",
          "hostname": "lb-haproxy-pus-01.openmanager.kr",
          "type": "loadbalancer",
          "location": "Busan-PUS-DR",
          "environment": "production",
          "status": "online",
          "cpu": 35,
          "memory": 36,
          "disk": 14,
          "network": 63,
          "responseTime": 140,
          "uptime": 2642556,
          "ip": "10.20.6.11",
          "os": "Ubuntu 22.04 LTS",
          "specs": {
            "cpu_cores": 4,
            "memory_gb": 8,
            "disk_gb": 50
          },
          "services": [],
          "processes": 142,
          "logs": []
        }
      }
    },
    {
      "minute": 30,
      "timestamp": "00:30",
      "servers": {
        "web-nginx-icn-01": {
          "id": "web-nginx-icn-01",
          "name": "Nginx Web Server 01",
          "hostname": "web-nginx-icn-01.openmanager.kr",
          "type": "web",
          "location": "Seoul-ICN-AZ1",
          "environment": "production",
          "status": "warning",
          "cpu": 78,
          "memory": 41,
          "disk": 29,
          "network": 55,
          "responseTime": 200,
          "uptime": 2633573,
          "ip": "10.10.1.11",
          "os": "Ubuntu 22.04 LTS",
          "specs": {
            "cpu_cores": 4,
            "memory_gb": 8,
            "disk_gb": 100
          },
          "services": [
            {
              "name": "nginx",
              "status": "running",
              "health": "warning",
              "message": "Elevated cpu usage"
            },
            {
              "name": "php-fpm",
              "status": "running",
              "health": "warning",
              "message": "Elevated cpu usage"
            }
          ],
          "processes": 175,
          "logs": [
            {
              "timestamp": "00:30:00",
              "level": "WARN",
              "message": "[WARNING] CPU usage at 78% - 새벽 배치 크론 작업으로 CPU 증가"
            }
          ]
        },
        "web-nginx-icn-02": {
          "id": "web-nginx-icn-02",
          "name": "Nginx Web Server 02",
          "hostname": "web-nginx-icn-02.openmanager.kr",
          "type": "web",
          "location": "Seoul-ICN-AZ2",
          "environment": "production",
          "status": "online",
          "cpu": 29,
          "memory": 45,
          "disk": 26,
          "network": 58,
          "responseTime": 139,
          "uptime": 2610134,
          "ip": "10.10.1.12",
          "os": "Ubuntu 22.04 LTS",
          "specs": {
            "cpu_cores": 4,
            "memory_gb": 8,
            "disk_gb": 100
          },
          "services": [],
          "processes": 123,
          "logs": []
        },
        "web-nginx-pus-01": {
          "id": "web-nginx-pus-01",
          "name": "Nginx Web Server DR",
          "hostname": "web-nginx-pus-01.openmanager.kr",
          "type": "web",
          "location": "Busan-PUS-AZ1",
          "environment": "production",
          "status": "online",
          "cpu": 22,
          "memory": 33,
          "disk": 24,
          "network": 35,
          "responseTime": 160,
          "uptime": 2674995,
          "ip": "10.20.1.11",
          "os": "Ubuntu 22.04 LTS",
          "specs": {
            "cpu_cores": 4,
            "memory_gb": 8,
            "disk_gb": 100
          },
          "services": [],
          "processes": 137,
          "logs": []
        },
        "api-was-icn-01": {
          "id": "api-was-icn-01",
          "name": "WAS API Server 01",
          "hostname": "api-was-icn-01.openmanager.kr",
          "type": "application",
          "location": "Seoul-ICN-AZ1",
          "environment": "production",
          "status": "online",
          "cpu": 49,
          "memory": 57,
          "disk": 34,
          "network": 50,
          "responseTime": 141,
          "uptime": 2648659,
          "ip": "10.10.2.11",
          "os": "Ubuntu 22.04 LTS",
          "specs": {
            "cpu_cores": 8,
            "memory_gb": 16,
            "disk_gb": 200
          },
          "services": [],
          "processes": 115,
          "logs": []
        },
        "api-was-icn-02": {
          "id": "api-was-icn-02",
          "name": "WAS API Server 02",
          "hostname": "api-was-icn-02.openmanager.kr",
          "type": "application",
          "location": "Seoul-ICN-AZ2",
          "environment": "production",
          "status": "online",
          "cpu": 40,
          "memory": 49,
          "disk": 31,
          "network": 44,
          "responseTime": 157,
          "uptime": 2635105,
          "ip": "10.10.2.12",
          "os": "Ubuntu 22.04 LTS",
          "specs": {
            "cpu_cores": 8,
            "memory_gb": 16,
            "disk_gb": 200
          },
          "services": [],
          "processes": 100,
          "logs": []
        },
        "api-was-pus-01": {
          "id": "api-was-pus-01",
          "name": "WAS API Server DR",
          "hostname": "api-was-pus-01.openmanager.kr",
          "type": "application",
          "location": "Busan-PUS-AZ1",
          "environment": "production",
          "status": "online",
          "cpu": 22,
          "memory": 41,
          "disk": 29,
          "network": 34,
          "responseTime": 136,
          "uptime": 2675097,
          "ip": "10.20.2.11",
          "os": "Ubuntu 22.04 LTS",
          "specs": {
            "cpu_cores": 8,
            "memory_gb": 16,
            "disk_gb": 200
          },
          "services": [],
          "processes": 101,
          "logs": []
        },
        "db-mysql-icn-primary": {
          "id": "db-mysql-icn-primary",
          "name": "MySQL Primary",
          "hostname": "db-mysql-icn-primary.openmanager.kr",
          "type": "database",
          "location": "Seoul-ICN-AZ1",
          "environment": "production",
          "status": "critical",
          "cpu": 59,
          "memory": 68,
          "disk": 92,
          "network": 44,
          "responseTime": 380,
          "uptime": 2610780,
          "ip": "10.10.3.11",
          "os": "Ubuntu 22.04 LTS",
          "specs": {
            "cpu_cores": 16,
            "memory_gb": 64,
            "disk_gb": 1000
          },
          "services": [
            {
              "name": "mysqld",
              "status": "degraded",
              "health": "critical",
              "message": "High disk usage affecting mysqld"
            },
            {
              "name": "mysql-router",
              "status": "degraded",
              "health": "critical",
              "message": "High disk usage affecting mysql-router"
            }
          ],
          "processes": 123,
          "logs": [
            {
              "timestamp": "00:30:00",
              "level": "ERROR",
              "message": "[CRITICAL] DISK usage reached 92% - 새벽 자동 백업 + 바이너리 로그 누적으로 디스크 위험"
            },
            {
              "timestamp": "00:31:00",
              "level": "WARN",
              "message": "[ALERT] Threshold exceeded: disk > 90%. Immediate action required."
            }
          ]
        },
        "db-mysql-icn-replica": {
          "id": "db-mysql-icn-replica",
          "name": "MySQL Replica",
          "hostname": "db-mysql-icn-replica.openmanager.kr",
          "type": "database",
          "location": "Seoul-ICN-AZ2",
          "environment": "production",
          "status": "online",
          "cpu": 40,
          "memory": 59,
          "disk": 44,
          "network": 39,
          "responseTime": 44,
          "uptime": 2639237,
          "ip": "10.10.3.12",
          "os": "Ubuntu 22.04 LTS",
          "specs": {
            "cpu_cores": 16,
            "memory_gb": 64,
            "disk_gb": 1000
          },
          "services": [],
          "processes": 139,
          "logs": []
        },
        "db-mysql-pus-dr": {
          "id": "db-mysql-pus-dr",
          "name": "MySQL DR Replica",
          "hostname": "db-mysql-pus-dr.openmanager.kr",
          "type": "database",
          "location": "Busan-PUS-AZ1",
          "environment": "production",
          "status": "online",
          "cpu": 20,
          "memory": 45,
          "disk": 39,
          "network": 22,
          "responseTime": 58,
          "uptime": 2595982,
          "ip": "10.20.3.11",
          "os": "Ubuntu 22.04 LTS",
          "specs": {
            "cpu_cores": 16,
            "memory_gb": 64,
            "disk_gb": 1000
          },
          "services": [],
          "processes": 113,
          "logs": []
        },
        "cache-redis-icn-01": {
          "id": "cache-redis-icn-01",
          "name": "Redis Cache 01",
          "hostname": "cache-redis-icn-01.openmanager.kr",
          "type": "cache",
          "location": "Seoul-ICN-AZ1",
          "environment": "production",
          "status": "warning",
          "cpu": 23,
          "memory": 88,
          "disk": 22,
          "network": 43,
          "responseTime": 200,
          "uptime": 2648854,
          "ip": "10.10.4.11",
          "os": "Ubuntu 22.04 LTS",
          "specs": {
            "cpu_cores": 4,
            "memory_gb": 32,
            "disk_gb": 50
          },
          "services": [
            {
              "name": "redis-server",
              "status": "running",
              "health": "warning",
              "message": "Elevated memory usage"
            },
            {
              "name": "redis-sentinel",
              "status": "running",
              "health": "warning",
              "message": "Elevated memory usage"
            }
          ],
          "processes": 119,
          "logs": [
            {
              "timestamp": "00:30:00",
              "level": "WARN",
              "message": "[WARNING] MEMORY usage at 88% - Redis 캐시 메모리 누적으로 경고 수준"
            }
          ]
        },
        "cache-redis-icn-02": {
          "id": "cache-redis-icn-02",
          "name": "Redis Cache 02",
          "hostname": "cache-redis-icn-02.openmanager.kr",
          "type": "cache",
          "location": "Seoul-ICN-AZ2",
          "environment": "production",
          "status": "online",
          "cpu": 20,
          "memory": 69,
          "disk": 20,
          "network": 46,
          "responseTime": 20,
          "uptime": 2666848,
          "ip": "10.10.4.12",
          "os": "Ubuntu 22.04 LTS",
          "specs": {
            "cpu_cores": 4,
            "memory_gb": 32,
            "disk_gb": 50
          },
          "services": [],
          "processes": 121,
          "logs": []
        },
        "storage-nfs-icn-01": {
          "id": "storage-nfs-icn-01",
          "name": "NFS Storage 01",
          "hostname": "storage-nfs-icn-01.openmanager.kr",
          "type": "storage",
          "location": "Seoul-ICN-AZ1",
          "environment": "production",
          "status": "online",
          "cpu": 31,
          "memory": 37,
          "disk": 63,
          "network": 45,
          "responseTime": 131,
          "uptime": 2622331,
          "ip": "10.10.5.11",
          "os": "Ubuntu 22.04 LTS",
          "specs": {
            "cpu_cores": 4,
            "memory_gb": 16,
            "disk_gb": 5000
          },
          "services": [],
          "processes": 106,
          "logs": []
        },
        "storage-s3gw-pus-01": {
          "id": "storage-s3gw-pus-01",
          "name": "S3 Gateway DR",
          "hostname": "storage-s3gw-pus-01.openmanager.kr",
          "type": "storage",
          "location": "Busan-PUS-DR",
          "environment": "production",
          "status": "online",
          "cpu": 19,
          "memory": 31,
          "disk": 54,
          "network": 56,
          "responseTime": 161,
          "uptime": 2605796,
          "ip": "10.20.5.11",
          "os": "Ubuntu 22.04 LTS",
          "specs": {
            "cpu_cores": 2,
            "memory_gb": 8,
            "disk_gb": 200
          },
          "services": [],
          "processes": 105,
          "logs": []
        },
        "lb-haproxy-icn-01": {
          "id": "lb-haproxy-icn-01",
          "name": "HAProxy LB 01",
          "hostname": "lb-haproxy-icn-01.openmanager.kr",
          "type": "loadbalancer",
          "location": "Seoul-ICN-AZ1",
          "environment": "production",
          "status": "online",
          "cpu": 44,
          "memory": 34,
          "disk": 15,
          "network": 68,
          "responseTime": 150,
          "uptime": 2614269,
          "ip": "10.10.6.11",
          "os": "Ubuntu 22.04 LTS",
          "specs": {
            "cpu_cores": 4,
            "memory_gb": 8,
            "disk_gb": 50
          },
          "services": [],
          "processes": 141,
          "logs": []
        },
        "lb-haproxy-pus-01": {
          "id": "lb-haproxy-pus-01",
          "name": "HAProxy LB DR",
          "hostname": "lb-haproxy-pus-01.openmanager.kr",
          "type": "loadbalancer",
          "location": "Busan-PUS-DR",
          "environment": "production",
          "status": "online",
          "cpu": 33,
          "memory": 31,
          "disk": 12,
          "network": 70,
          "responseTime": 120,
          "uptime": 2675664,
          "ip": "10.20.6.11",
          "os": "Ubuntu 22.04 LTS",
          "specs": {
            "cpu_cores": 4,
            "memory_gb": 8,
            "disk_gb": 50
          },
          "services": [],
          "processes": 108,
          "logs": []
        }
      }
    },
    {
      "minute": 40,
      "timestamp": "00:40",
      "servers": {
        "web-nginx-icn-01": {
          "id": "web-nginx-icn-01",
          "name": "Nginx Web Server 01",
          "hostname": "web-nginx-icn-01.openmanager.kr",
          "type": "web",
          "location": "Seoul-ICN-AZ1",
          "environment": "production",
          "status": "warning",
          "cpu": 78,
          "memory": 43,
          "disk": 28,
          "network": 55,
          "responseTime": 200,
          "uptime": 2635934,
          "ip": "10.10.1.11",
          "os": "Ubuntu 22.04 LTS",
          "specs": {
            "cpu_cores": 4,
            "memory_gb": 8,
            "disk_gb": 100
          },
          "services": [
            {
              "name": "nginx",
              "status": "running",
              "health": "warning",
              "message": "Elevated cpu usage"
            },
            {
              "name": "php-fpm",
              "status": "running",
              "health": "warning",
              "message": "Elevated cpu usage"
            }
          ],
          "processes": 175,
          "logs": [
            {
              "timestamp": "00:40:00",
              "level": "WARN",
              "message": "[WARNING] CPU usage at 78% - 새벽 배치 크론 작업으로 CPU 증가"
            }
          ]
        },
        "web-nginx-icn-02": {
          "id": "web-nginx-icn-02",
          "name": "Nginx Web Server 02",
          "hostname": "web-nginx-icn-02.openmanager.kr",
          "type": "web",
          "location": "Seoul-ICN-AZ2",
          "environment": "production",
          "status": "online",
          "cpu": 36,
          "memory": 45,
          "disk": 29,
          "network": 52,
          "responseTime": 146,
          "uptime": 2595515,
          "ip": "10.10.1.12",
          "os": "Ubuntu 22.04 LTS",
          "specs": {
            "cpu_cores": 4,
            "memory_gb": 8,
            "disk_gb": 100
          },
          "services": [],
          "processes": 142,
          "logs": []
        },
        "web-nginx-pus-01": {
          "id": "web-nginx-pus-01",
          "name": "Nginx Web Server DR",
          "hostname": "web-nginx-pus-01.openmanager.kr",
          "type": "web",
          "location": "Busan-PUS-AZ1",
          "environment": "production",
          "status": "online",
          "cpu": 20,
          "memory": 34,
          "disk": 23,
          "network": 37,
          "responseTime": 138,
          "uptime": 2659004,
          "ip": "10.20.1.11",
          "os": "Ubuntu 22.04 LTS",
          "specs": {
            "cpu_cores": 4,
            "memory_gb": 8,
            "disk_gb": 100
          },
          "services": [],
          "processes": 118,
          "logs": []
        },
        "api-was-icn-01": {
          "id": "api-was-icn-01",
          "name": "WAS API Server 01",
          "hostname": "api-was-icn-01.openmanager.kr",
          "type": "application",
          "location": "Seoul-ICN-AZ1",
          "environment": "production",
          "status": "online",
          "cpu": 44,
          "memory": 53,
          "disk": 36,
          "network": 50,
          "responseTime": 154,
          "uptime": 2646872,
          "ip": "10.10.2.11",
          "os": "Ubuntu 22.04 LTS",
          "specs": {
            "cpu_cores": 8,
            "memory_gb": 16,
            "disk_gb": 200
          },
          "services": [],
          "processes": 111,
          "logs": []
        },
        "api-was-icn-02": {
          "id": "api-was-icn-02",
          "name": "WAS API Server 02",
          "hostname": "api-was-icn-02.openmanager.kr",
          "type": "application",
          "location": "Seoul-ICN-AZ2",
          "environment": "production",
          "status": "online",
          "cpu": 40,
          "memory": 55,
          "disk": 31,
          "network": 44,
          "responseTime": 150,
          "uptime": 2645634,
          "ip": "10.10.2.12",
          "os": "Ubuntu 22.04 LTS",
          "specs": {
            "cpu_cores": 8,
            "memory_gb": 16,
            "disk_gb": 200
          },
          "services": [],
          "processes": 136,
          "logs": []
        },
        "api-was-pus-01": {
          "id": "api-was-pus-01",
          "name": "WAS API Server DR",
          "hostname": "api-was-pus-01.openmanager.kr",
          "type": "application",
          "location": "Busan-PUS-AZ1",
          "environment": "production",
          "status": "online",
          "cpu": 29,
          "memory": 42,
          "disk": 29,
          "network": 34,
          "responseTime": 153,
          "uptime": 2593050,
          "ip": "10.20.2.11",
          "os": "Ubuntu 22.04 LTS",
          "specs": {
            "cpu_cores": 8,
            "memory_gb": 16,
            "disk_gb": 200
          },
          "services": [],
          "processes": 117,
          "logs": []
        },
        "db-mysql-icn-primary": {
          "id": "db-mysql-icn-primary",
          "name": "MySQL Primary",
          "hostname": "db-mysql-icn-primary.openmanager.kr",
          "type": "database",
          "location": "Seoul-ICN-AZ1",
          "environment": "production",
          "status": "critical",
          "cpu": 50,
          "memory": 68,
          "disk": 92,
          "network": 37,
          "responseTime": 380,
          "uptime": 2647235,
          "ip": "10.10.3.11",
          "os": "Ubuntu 22.04 LTS",
          "specs": {
            "cpu_cores": 16,
            "memory_gb": 64,
            "disk_gb": 1000
          },
          "services": [
            {
              "name": "mysqld",
              "status": "degraded",
              "health": "critical",
              "message": "High disk usage affecting mysqld"
            },
            {
              "name": "mysql-router",
              "status": "degraded",
              "health": "critical",
              "message": "High disk usage affecting mysql-router"
            }
          ],
          "processes": 111,
          "logs": [
            {
              "timestamp": "00:40:00",
              "level": "ERROR",
              "message": "[CRITICAL] DISK usage reached 92% - 새벽 자동 백업 + 바이너리 로그 누적으로 디스크 위험"
            },
            {
              "timestamp": "00:41:00",
              "level": "WARN",
              "message": "[ALERT] Threshold exceeded: disk > 90%. Immediate action required."
            }
          ]
        },
        "db-mysql-icn-replica": {
          "id": "db-mysql-icn-replica",
          "name": "MySQL Replica",
          "hostname": "db-mysql-icn-replica.openmanager.kr",
          "type": "database",
          "location": "Seoul-ICN-AZ2",
          "environment": "production",
          "status": "online",
          "cpu": 35,
          "memory": 61,
          "disk": 40,
          "network": 30,
          "responseTime": 46,
          "uptime": 2607690,
          "ip": "10.10.3.12",
          "os": "Ubuntu 22.04 LTS",
          "specs": {
            "cpu_cores": 16,
            "memory_gb": 64,
            "disk_gb": 1000
          },
          "services": [],
          "processes": 105,
          "logs": []
        },
        "db-mysql-pus-dr": {
          "id": "db-mysql-pus-dr",
          "name": "MySQL DR Replica",
          "hostname": "db-mysql-pus-dr.openmanager.kr",
          "type": "database",
          "location": "Busan-PUS-AZ1",
          "environment": "production",
          "status": "online",
          "cpu": 24,
          "memory": 45,
          "disk": 38,
          "network": 26,
          "responseTime": 57,
          "uptime": 2615833,
          "ip": "10.20.3.11",
          "os": "Ubuntu 22.04 LTS",
          "specs": {
            "cpu_cores": 16,
            "memory_gb": 64,
            "disk_gb": 1000
          },
          "services": [],
          "processes": 113,
          "logs": []
        },
        "cache-redis-icn-01": {
          "id": "cache-redis-icn-01",
          "name": "Redis Cache 01",
          "hostname": "cache-redis-icn-01.openmanager.kr",
          "type": "cache",
          "location": "Seoul-ICN-AZ1",
          "environment": "production",
          "status": "warning",
          "cpu": 29,
          "memory": 88,
          "disk": 19,
          "network": 44,
          "responseTime": 200,
          "uptime": 2667337,
          "ip": "10.10.4.11",
          "os": "Ubuntu 22.04 LTS",
          "specs": {
            "cpu_cores": 4,
            "memory_gb": 32,
            "disk_gb": 50
          },
          "services": [
            {
              "name": "redis-server",
              "status": "running",
              "health": "warning",
              "message": "Elevated memory usage"
            },
            {
              "name": "redis-sentinel",
              "status": "running",
              "health": "warning",
              "message": "Elevated memory usage"
            }
          ],
          "processes": 129,
          "logs": [
            {
              "timestamp": "00:40:00",
              "level": "WARN",
              "message": "[WARNING] MEMORY usage at 88% - Redis 캐시 메모리 누적으로 경고 수준"
            }
          ]
        },
        "cache-redis-icn-02": {
          "id": "cache-redis-icn-02",
          "name": "Redis Cache 02",
          "hostname": "cache-redis-icn-02.openmanager.kr",
          "type": "cache",
          "location": "Seoul-ICN-AZ2",
          "environment": "production",
          "status": "online",
          "cpu": 18,
          "memory": 70,
          "disk": 17,
          "network": 43,
          "responseTime": 20,
          "uptime": 2593090,
          "ip": "10.10.4.12",
          "os": "Ubuntu 22.04 LTS",
          "specs": {
            "cpu_cores": 4,
            "memory_gb": 32,
            "disk_gb": 50
          },
          "services": [],
          "processes": 127,
          "logs": []
        },
        "storage-nfs-icn-01": {
          "id": "storage-nfs-icn-01",
          "name": "NFS Storage 01",
          "hostname": "storage-nfs-icn-01.openmanager.kr",
          "type": "storage",
          "location": "Seoul-ICN-AZ1",
          "environment": "production",
          "status": "online",
          "cpu": 25,
          "memory": 36,
          "disk": 65,
          "network": 47,
          "responseTime": 133,
          "uptime": 2612921,
          "ip": "10.10.5.11",
          "os": "Ubuntu 22.04 LTS",
          "specs": {
            "cpu_cores": 4,
            "memory_gb": 16,
            "disk_gb": 5000
          },
          "services": [],
          "processes": 130,
          "logs": []
        },
        "storage-s3gw-pus-01": {
          "id": "storage-s3gw-pus-01",
          "name": "S3 Gateway DR",
          "hostname": "storage-s3gw-pus-01.openmanager.kr",
          "type": "storage",
          "location": "Busan-PUS-DR",
          "environment": "production",
          "status": "online",
          "cpu": 18,
          "memory": 36,
          "disk": 52,
          "network": 63,
          "responseTime": 178,
          "uptime": 2633969,
          "ip": "10.20.5.11",
          "os": "Ubuntu 22.04 LTS",
          "specs": {
            "cpu_cores": 2,
            "memory_gb": 8,
            "disk_gb": 200
          },
          "services": [],
          "processes": 137,
          "logs": []
        },
        "lb-haproxy-icn-01": {
          "id": "lb-haproxy-icn-01",
          "name": "HAProxy LB 01",
          "hostname": "lb-haproxy-icn-01.openmanager.kr",
          "type": "loadbalancer",
          "location": "Seoul-ICN-AZ1",
          "environment": "production",
          "status": "online",
          "cpu": 44,
          "memory": 31,
          "disk": 17,
          "network": 72,
          "responseTime": 131,
          "uptime": 2661317,
          "ip": "10.10.6.11",
          "os": "Ubuntu 22.04 LTS",
          "specs": {
            "cpu_cores": 4,
            "memory_gb": 8,
            "disk_gb": 50
          },
          "services": [],
          "processes": 102,
          "logs": []
        },
        "lb-haproxy-pus-01": {
          "id": "lb-haproxy-pus-01",
          "name": "HAProxy LB DR",
          "hostname": "lb-haproxy-pus-01.openmanager.kr",
          "type": "loadbalancer",
          "location": "Busan-PUS-DR",
          "environment": "production",
          "status": "online",
          "cpu": 37,
          "memory": 30,
          "disk": 12,
          "network": 72,
          "responseTime": 134,
          "uptime": 2630923,
          "ip": "10.20.6.11",
          "os": "Ubuntu 22.04 LTS",
          "specs": {
            "cpu_cores": 4,
            "memory_gb": 8,
            "disk_gb": 50
          },
          "services": [],
          "processes": 140,
          "logs": []
        }
      }
    },
    {
      "minute": 50,
      "timestamp": "00:50",
      "servers": {
        "web-nginx-icn-01": {
          "id": "web-nginx-icn-01",
          "name": "Nginx Web Server 01",
          "hostname": "web-nginx-icn-01.openmanager.kr",
          "type": "web",
          "location": "Seoul-ICN-AZ1",
          "environment": "production",
          "status": "warning",
          "cpu": 78,
          "memory": 47,
          "disk": 28,
          "network": 61,
          "responseTime": 200,
          "uptime": 2643163,
          "ip": "10.10.1.11",
          "os": "Ubuntu 22.04 LTS",
          "specs": {
            "cpu_cores": 4,
            "memory_gb": 8,
            "disk_gb": 100
          },
          "services": [
            {
              "name": "nginx",
              "status": "running",
              "health": "warning",
              "message": "Elevated cpu usage"
            },
            {
              "name": "php-fpm",
              "status": "running",
              "health": "warning",
              "message": "Elevated cpu usage"
            }
          ],
          "processes": 175,
          "logs": [
            {
              "timestamp": "00:50:00",
              "level": "WARN",
              "message": "[WARNING] CPU usage at 78% - 새벽 배치 크론 작업으로 CPU 증가"
            }
          ]
        },
        "web-nginx-icn-02": {
          "id": "web-nginx-icn-02",
          "name": "Nginx Web Server 02",
          "hostname": "web-nginx-icn-02.openmanager.kr",
          "type": "web",
          "location": "Seoul-ICN-AZ2",
          "environment": "production",
          "status": "online",
          "cpu": 28,
          "memory": 40,
          "disk": 30,
          "network": 57,
          "responseTime": 157,
          "uptime": 2618919,
          "ip": "10.10.1.12",
          "os": "Ubuntu 22.04 LTS",
          "specs": {
            "cpu_cores": 4,
            "memory_gb": 8,
            "disk_gb": 100
          },
          "services": [],
          "processes": 142,
          "logs": []
        },
        "web-nginx-pus-01": {
          "id": "web-nginx-pus-01",
          "name": "Nginx Web Server DR",
          "hostname": "web-nginx-pus-01.openmanager.kr",
          "type": "web",
          "location": "Busan-PUS-AZ1",
          "environment": "production",
          "status": "online",
          "cpu": 17,
          "memory": 38,
          "disk": 25,
          "network": 40,
          "responseTime": 145,
          "uptime": 2633455,
          "ip": "10.20.1.11",
          "os": "Ubuntu 22.04 LTS",
          "specs": {
            "cpu_cores": 4,
            "memory_gb": 8,
            "disk_gb": 100
          },
          "services": [],
          "processes": 134,
          "logs": []
        },
        "api-was-icn-01": {
          "id": "api-was-icn-01",
          "name": "WAS API Server 01",
          "hostname": "api-was-icn-01.openmanager.kr",
          "type": "application",
          "location": "Seoul-ICN-AZ1",
          "environment": "production",
          "status": "online",
          "cpu": 46,
          "memory": 54,
          "disk": 33,
          "network": 50,
          "responseTime": 142,
          "uptime": 2604370,
          "ip": "10.10.2.11",
          "os": "Ubuntu 22.04 LTS",
          "specs": {
            "cpu_cores": 8,
            "memory_gb": 16,
            "disk_gb": 200
          },
          "services": [],
          "processes": 101,
          "logs": []
        },
        "api-was-icn-02": {
          "id": "api-was-icn-02",
          "name": "WAS API Server 02",
          "hostname": "api-was-icn-02.openmanager.kr",
          "type": "application",
          "location": "Seoul-ICN-AZ2",
          "environment": "production",
          "status": "online",
          "cpu": 46,
          "memory": 49,
          "disk": 34,
          "network": 47,
          "responseTime": 122,
          "uptime": 2651284,
          "ip": "10.10.2.12",
          "os": "Ubuntu 22.04 LTS",
          "specs": {
            "cpu_cores": 8,
            "memory_gb": 16,
            "disk_gb": 200
          },
          "services": [],
          "processes": 145,
          "logs": []
        },
        "api-was-pus-01": {
          "id": "api-was-pus-01",
          "name": "WAS API Server DR",
          "hostname": "api-was-pus-01.openmanager.kr",
          "type": "application",
          "location": "Busan-PUS-AZ1",
          "environment": "production",
          "status": "online",
          "cpu": 20,
          "memory": 42,
          "disk": 28,
          "network": 31,
          "responseTime": 173,
          "uptime": 2623596,
          "ip": "10.20.2.11",
          "os": "Ubuntu 22.04 LTS",
          "specs": {
            "cpu_cores": 8,
            "memory_gb": 16,
            "disk_gb": 200
          },
          "services": [],
          "processes": 126,
          "logs": []
        },
        "db-mysql-icn-primary": {
          "id": "db-mysql-icn-primary",
          "name": "MySQL Primary",
          "hostname": "db-mysql-icn-primary.openmanager.kr",
          "type": "database",
          "location": "Seoul-ICN-AZ1",
          "environment": "production",
          "status": "critical",
          "cpu": 51,
          "memory": 66,
          "disk": 92,
          "network": 41,
          "responseTime": 380,
          "uptime": 2626752,
          "ip": "10.10.3.11",
          "os": "Ubuntu 22.04 LTS",
          "specs": {
            "cpu_cores": 16,
            "memory_gb": 64,
            "disk_gb": 1000
          },
          "services": [
            {
              "name": "mysqld",
              "status": "degraded",
              "health": "critical",
              "message": "High disk usage affecting mysqld"
            },
            {
              "name": "mysql-router",
              "status": "degraded",
              "health": "critical",
              "message": "High disk usage affecting mysql-router"
            }
          ],
          "processes": 145,
          "logs": [
            {
              "timestamp": "00:50:00",
              "level": "ERROR",
              "message": "[CRITICAL] DISK usage reached 92% - 새벽 자동 백업 + 바이너리 로그 누적으로 디스크 위험"
            },
            {
              "timestamp": "00:51:00",
              "level": "WARN",
              "message": "[ALERT] Threshold exceeded: disk > 90%. Immediate action required."
            }
          ]
        },
        "db-mysql-icn-replica": {
          "id": "db-mysql-icn-replica",
          "name": "MySQL Replica",
          "hostname": "db-mysql-icn-replica.openmanager.kr",
          "type": "database",
          "location": "Seoul-ICN-AZ2",
          "environment": "production",
          "status": "online",
          "cpu": 38,
          "memory": 61,
          "disk": 40,
          "network": 33,
          "responseTime": 41,
          "uptime": 2651896,
          "ip": "10.10.3.12",
          "os": "Ubuntu 22.04 LTS",
          "specs": {
            "cpu_cores": 16,
            "memory_gb": 64,
            "disk_gb": 1000
          },
          "services": [],
          "processes": 136,
          "logs": []
        },
        "db-mysql-pus-dr": {
          "id": "db-mysql-pus-dr",
          "name": "MySQL DR Replica",
          "hostname": "db-mysql-pus-dr.openmanager.kr",
          "type": "database",
          "location": "Busan-PUS-AZ1",
          "environment": "production",
          "status": "online",
          "cpu": 23,
          "memory": 47,
          "disk": 39,
          "network": 29,
          "responseTime": 50,
          "uptime": 2610845,
          "ip": "10.20.3.11",
          "os": "Ubuntu 22.04 LTS",
          "specs": {
            "cpu_cores": 16,
            "memory_gb": 64,
            "disk_gb": 1000
          },
          "services": [],
          "processes": 100,
          "logs": []
        },
        "cache-redis-icn-01": {
          "id": "cache-redis-icn-01",
          "name": "Redis Cache 01",
          "hostname": "cache-redis-icn-01.openmanager.kr",
          "type": "cache",
          "location": "Seoul-ICN-AZ1",
          "environment": "production",
          "status": "warning",
          "cpu": 23,
          "memory": 88,
          "disk": 20,
          "network": 43,
          "responseTime": 200,
          "uptime": 2609442,
          "ip": "10.10.4.11",
          "os": "Ubuntu 22.04 LTS",
          "specs": {
            "cpu_cores": 4,
            "memory_gb": 32,
            "disk_gb": 50
          },
          "services": [
            {
              "name": "redis-server",
              "status": "running",
              "health": "warning",
              "message": "Elevated memory usage"
            },
            {
              "name": "redis-sentinel",
              "status": "running",
              "health": "warning",
              "message": "Elevated memory usage"
            }
          ],
          "processes": 102,
          "logs": [
            {
              "timestamp": "00:50:00",
              "level": "WARN",
              "message": "[WARNING] MEMORY usage at 88% - Redis 캐시 메모리 누적으로 경고 수준"
            }
          ]
        },
        "cache-redis-icn-02": {
          "id": "cache-redis-icn-02",
          "name": "Redis Cache 02",
          "hostname": "cache-redis-icn-02.openmanager.kr",
          "type": "cache",
          "location": "Seoul-ICN-AZ2",
          "environment": "production",
          "status": "online",
          "cpu": 21,
          "memory": 73,
          "disk": 18,
          "network": 42,
          "responseTime": 22,
          "uptime": 2620669,
          "ip": "10.10.4.12",
          "os": "Ubuntu 22.04 LTS",
          "specs": {
            "cpu_cores": 4,
            "memory_gb": 32,
            "disk_gb": 50
          },
          "services": [],
          "processes": 112,
          "logs": []
        },
        "storage-nfs-icn-01": {
          "id": "storage-nfs-icn-01",
          "name": "NFS Storage 01",
          "hostname": "storage-nfs-icn-01.openmanager.kr",
          "type": "storage",
          "location": "Seoul-ICN-AZ1",
          "environment": "production",
          "status": "online",
          "cpu": 29,
          "memory": 39,
          "disk": 66,
          "network": 49,
          "responseTime": 172,
          "uptime": 2674563,
          "ip": "10.10.5.11",
          "os": "Ubuntu 22.04 LTS",
          "specs": {
            "cpu_cores": 4,
            "memory_gb": 16,
            "disk_gb": 5000
          },
          "services": [],
          "processes": 109,
          "logs": []
        },
        "storage-s3gw-pus-01": {
          "id": "storage-s3gw-pus-01",
          "name": "S3 Gateway DR",
          "hostname": "storage-s3gw-pus-01.openmanager.kr",
          "type": "storage",
          "location": "Busan-PUS-DR",
          "environment": "production",
          "status": "online",
          "cpu": 18,
          "memory": 35,
          "disk": 56,
          "network": 55,
          "responseTime": 129,
          "uptime": 2655504,
          "ip": "10.20.5.11",
          "os": "Ubuntu 22.04 LTS",
          "specs": {
            "cpu_cores": 2,
            "memory_gb": 8,
            "disk_gb": 200
          },
          "services": [],
          "processes": 132,
          "logs": []
        },
        "lb-haproxy-icn-01": {
          "id": "lb-haproxy-icn-01",
          "name": "HAProxy LB 01",
          "hostname": "lb-haproxy-icn-01.openmanager.kr",
          "type": "loadbalancer",
          "location": "Seoul-ICN-AZ1",
          "environment": "production",
          "status": "online",
          "cpu": 40,
          "memory": 34,
          "disk": 16,
          "network": 73,
          "responseTime": 136,
          "uptime": 2638549,
          "ip": "10.10.6.11",
          "os": "Ubuntu 22.04 LTS",
          "specs": {
            "cpu_cores": 4,
            "memory_gb": 8,
            "disk_gb": 50
          },
          "services": [],
          "processes": 147,
          "logs": []
        },
        "lb-haproxy-pus-01": {
          "id": "lb-haproxy-pus-01",
          "name": "HAProxy LB DR",
          "hostname": "lb-haproxy-pus-01.openmanager.kr",
          "type": "loadbalancer",
          "location": "Busan-PUS-DR",
          "environment": "production",
          "status": "online",
          "cpu": 38,
          "memory": 35,
          "disk": 15,
          "network": 66,
          "responseTime": 120,
          "uptime": 2596100,
          "ip": "10.20.6.11",
          "os": "Ubuntu 22.04 LTS",
          "specs": {
            "cpu_cores": 4,
            "memory_gb": 8,
            "disk_gb": 50
          },
          "services": [],
          "processes": 105,
          "logs": []
        }
      }
    }
  ],
  "metadata": {
    "version": "2.1.0",
    "totalDataPoints": 6,
    "intervalMinutes": 10,
    "serverCount": 15,
    "affectedServers": 0,
    "hasPreFailureSymptoms": false,
    "hasRecoveryPhase": false
  }
}
